cosmic-flagger/__init__.py
cosmic-flagger/cosmic_flagger.py
cosmic_flagger/__init__.py
cosmic_flagger/cosmic_flagger.py
cosmic_flagger-0.2.0.dist-info/METADATA
cosmic_flagger-0.2.0.dist-info/WHEEL
cosmic_flagger-0.2.0.dist-info/top_level.txt
cosmic_flagger-0.2.0.dist-info/RECORD
